icdump.cpython-310-darwin.so
icdump-1.1.0.data/scripts/readobjc.py
icdump-1.1.0.dist-info/METADATA
icdump-1.1.0.dist-info/WHEEL
icdump-1.1.0.dist-info/top_level.txt
icdump-1.1.0.dist-info/RECORD
