Metadata-Version: 2.1
Name: icdump
Version: 1.1.0
Summary: A modern Objective-C class dump
Home-page: https://github.com/romainthomas/iCDump
Author: Romain Thomas
Author-email: me@romainthomas.fr
License: Apache License 2.0
Keywords: reverse-engineering,objective-c
Classifier: Development Status :: 4 - Beta
Classifier: Programming Language :: Python
Classifier: Programming Language :: C++
Classifier: Topic :: Software Development :: Libraries
Requires-Python: >=3.8
